[{"price": 1800, "area": 65.0, "unitPrice": 27.69, "buildingYear": 1979, "age": 46, "floorPlan": "３ＬＤＫ", "structure": "ＲＣ", "district": "東千葉", "period": "2025年第3四半期", "walkMinutes": 10}, {"price": 1800, "area": 75.0, "unitPrice": 24.0, "buildingYear": 1983, "age": 42, "floorPlan": "２ＬＤＫ", "structure": "ＳＲＣ", "district": "東千葉", "period": "2025年第3四半期", "walkMinutes": 10}, {"price": 3600, "area": 75.0, "unitPrice": 48.0, "buildingYear": 2020, "age": 5, "floorPlan": "３ＬＤＫ", "structure": "ＲＣ", "district": "椿森", "period": "2025年第3四半期", "walkMinutes": 4}, {"price": 3700, "area": 85.0, "unitPrice": 43.53, "buildingYear": 2010, "age": 15, "floorPlan": "３ＬＤＫ", "structure": "鉄骨造", "district": "椿森", "period": "2025年第3四半期", "walkMinutes": 9}, {"price": 3600, "area": 70.0, "unitPrice": 51.43, "buildingYear": 2020, "age": 5, "floorPlan": "３ＬＤＫ", "structure": "", "district": "椿森", "period": "2025年第3四半期", "walkMinutes": 5}, {"price": 1700, "area": 60.0, "unitPrice": 28.33, "buildingYear": 1979, "age": 46, "floorPlan": "３ＬＤＫ", "structure": "ＲＣ", "district": "東千葉", "period": "2025年第3四半期", "walkMinutes": 10}, {"price": 1500, "area": 80.0, "unitPrice": 18.75, "buildingYear": 1977, "age": 48, "floorPlan": "３ＬＤＫ", "structure": "ＲＣ", "district": "東千葉", "period": "2025年第3四半期", "walkMinutes": 10}, {"price": 1800, "area": 70.0, "unitPrice": 25.71, "buildingYear": null, "age": null, "floorPlan": "２ＬＤＫ", "structure": "", "district": "東千葉", "period": "2025年第3四半期", "walkMinutes": 10}, {"price": 900, "area": 90.0, "unitPrice": 10.0, "buildingYear": 1983, "age": 42, "floorPlan": "４ＬＤＫ＋Ｓ", "structure": "ＳＲＣ", "district": "高品町", "period": "2025年第3四半期", "walkMinutes": 18}, {"price": 1300, "area": 70.0, "unitPrice": 18.57, "buildingYear": 1997, "age": 28, "floorPlan": "３ＬＤＫ", "structure": "ＳＲＣ", "district": "高品町", "period": "2025年第3四半期", "walkMinutes": 23}, {"price": 1200, "area": 85.0, "unitPrice": 14.12, "buildingYear": 1989, "age": 36, "floorPlan": "３ＬＤＫ", "structure": "ＲＣ", "district": "東千葉", "period": "2025年第2四半期", "walkMinutes": 12}, {"price": 1700, "area": 85.0, "unitPrice": 20.0, "buildingYear": 1984, "age": 41, "floorPlan": "４ＬＤＫ", "structure": "ＳＲＣ", "district": "祐光", "period": "2025年第2四半期", "walkMinutes": 3}, {"price": 3900, "area": 75.0, "unitPrice": 52.0, "buildingYear": 2020, "age": 5, "floorPlan": "３ＬＤＫ", "structure": "ＲＣ", "district": "椿森", "period": "2025年第2四半期", "walkMinutes": 4}, {"price": 1400, "area": 70.0, "unitPrice": 20.0, "buildingYear": 2001, "age": 24, "floorPlan": "３ＬＤＫ", "structure": "ＳＲＣ", "district": "椿森", "period": "2025年第2四半期", "walkMinutes": 9}, {"price": 1200, "area": 55.0, "unitPrice": 21.82, "buildingYear": 1989, "age": 36, "floorPlan": "２ＤＫ＋Ｓ", "structure": "ＲＣ", "district": "道場北", "period": "2025年第2四半期", "walkMinutes": 10}, {"price": 1500, "area": 55.0, "unitPrice": 27.27, "buildingYear": 1989, "age": 36, "floorPlan": "３ＤＫ", "structure": "ＲＣ", "district": "道場北", "period": "2025年第2四半期", "walkMinutes": 10}, {"price": 2000, "area": 100.0, "unitPrice": 20.0, "buildingYear": 1989, "age": 36, "floorPlan": "４ＬＤＫ", "structure": "ＲＣ", "district": "道場北", "period": "2025年第2四半期", "walkMinutes": 14}, {"price": 460, "area": 15.0, "unitPrice": 30.67, "buildingYear": 1989, "age": 36, "floorPlan": "１Ｋ", "structure": "ＲＣ", "district": "要町", "period": "2025年第2四半期", "walkMinutes": 1}, {"price": 1800, "area": 75.0, "unitPrice": 24.0, "buildingYear": 1989, "age": 36, "floorPlan": "３ＬＤＫ", "structure": "ＲＣ", "district": "道場北", "period": "2025年第2四半期", "walkMinutes": 14}, {"price": 1400, "area": 75.0, "unitPrice": 18.67, "buildingYear": 1994, "age": 31, "floorPlan": "２ＬＤＫ", "structure": "ＲＣ", "district": "東千葉", "period": "2025年第1四半期", "walkMinutes": 12}, {"price": 2400, "area": 75.0, "unitPrice": 32.0, "buildingYear": 1983, "age": 42, "floorPlan": "３ＬＤＫ", "structure": "ＳＲＣ", "district": "東千葉", "period": "2025年第1四半期", "walkMinutes": 10}, {"price": 1400, "area": 75.0, "unitPrice": 18.67, "buildingYear": 1994, "age": 31, "floorPlan": "２ＬＤＫ", "structure": "ＲＣ", "district": "東千葉", "period": "2025年第1四半期", "walkMinutes": 12}, {"price": 2200, "area": 70.0, "unitPrice": 31.43, "buildingYear": 2001, "age": 24, "floorPlan": "３ＬＤＫ", "structure": "ＳＲＣ", "district": "椿森", "period": "2025年第1四半期", "walkMinutes": 9}, {"price": 1800, "area": 80.0, "unitPrice": 22.5, "buildingYear": 1989, "age": 36, "floorPlan": "３ＬＤＫ", "structure": "ＲＣ", "district": "道場北", "period": "2025年第1四半期", "walkMinutes": null}, {"price": 2200, "area": 65.0, "unitPrice": 33.85, "buildingYear": 2001, "age": 24, "floorPlan": "３ＬＤＫ", "structure": "ＳＲＣ", "district": "椿森", "period": "2025年第1四半期", "walkMinutes": 10}, {"price": 2000, "area": 55.0, "unitPrice": 36.36, "buildingYear": 2001, "age": 24, "floorPlan": "２ＬＤＫ", "structure": "ＳＲＣ", "district": "椿森", "period": "2025年第1四半期", "walkMinutes": 10}, {"price": 2100, "area": 65.0, "unitPrice": 32.31, "buildingYear": 2001, "age": 24, "floorPlan": "３ＬＤＫ", "structure": "ＳＲＣ", "district": "椿森", "period": "2025年第1四半期", "walkMinutes": 10}, {"price": 1900, "area": 65.0, "unitPrice": 29.23, "buildingYear": 1978, "age": 47, "floorPlan": "１ＬＤＫ", "structure": "ＲＣ", "district": "東千葉", "period": "2025年第1四半期", "walkMinutes": 8}, {"price": 1300, "area": 60.0, "unitPrice": 21.67, "buildingYear": 1994, "age": 31, "floorPlan": "２ＬＤＫ", "structure": "ＲＣ", "district": "東千葉", "period": "2025年第1四半期", "walkMinutes": 15}, {"price": 840, "area": 65.0, "unitPrice": 12.92, "buildingYear": 1978, "age": 47, "floorPlan": "３ＬＤＫ", "structure": "ＲＣ", "district": "東千葉", "period": "2025年第1四半期", "walkMinutes": 8}, {"price": 3000, "area": 65.0, "unitPrice": 46.15, "buildingYear": 1998, "age": 27, "floorPlan": "３ＬＤＫ", "structure": "ＲＣ", "district": "祐光", "period": "2025年第1四半期", "walkMinutes": 5}, {"price": 870, "area": 90.0, "unitPrice": 9.67, "buildingYear": 1983, "age": 42, "floorPlan": "４ＬＤＫ＋Ｓ", "structure": "ＳＲＣ", "district": "高品町", "period": "2025年第1四半期", "walkMinutes": 19}, {"price": 1500, "area": 70.0, "unitPrice": 21.43, "buildingYear": 2001, "age": 24, "floorPlan": "３ＬＤＫ", "structure": "ＲＣ", "district": "高品町", "period": "2025年第1四半期", "walkMinutes": 20}, {"price": 1600, "area": 65.0, "unitPrice": 24.62, "buildingYear": 1989, "age": 36, "floorPlan": "２ＬＤＫ", "structure": "ＲＣ", "district": "東千葉", "period": "2024年第4四半期", "walkMinutes": 12}, {"price": 600, "area": 55.0, "unitPrice": 10.91, "buildingYear": 1991, "age": 34, "floorPlan": "１ＬＤＫ", "structure": "ＲＣ", "district": "東千葉", "period": "2024年第4四半期", "walkMinutes": 14}, {"price": 1700, "area": 70.0, "unitPrice": 24.29, "buildingYear": 1994, "age": 31, "floorPlan": "２ＬＤＫ", "structure": "ＲＣ", "district": "東千葉", "period": "2024年第4四半期", "walkMinutes": 12}, {"price": 500, "area": 65.0, "unitPrice": 7.69, "buildingYear": 1979, "age": 46, "floorPlan": "３ＬＤＫ", "structure": "ＲＣ", "district": "東千葉", "period": "2024年第4四半期", "walkMinutes": 10}, {"price": 2400, "area": 75.0, "unitPrice": 32.0, "buildingYear": 2001, "age": 24, "floorPlan": "３ＬＤＫ", "structure": "ＲＣ", "district": "祐光", "period": "2024年第4四半期", "walkMinutes": 7}, {"price": 1500, "area": 70.0, "unitPrice": 21.43, "buildingYear": 1998, "age": 27, "floorPlan": "３ＬＤＫ", "structure": "ＲＣ", "district": "祐光", "period": "2024年第4四半期", "walkMinutes": 13}, {"price": 1400, "area": 80.0, "unitPrice": 17.5, "buildingYear": 1974, "age": 51, "floorPlan": "３ＬＤＫ", "structure": "ＲＣ", "district": "祐光", "period": "2024年第4四半期", "walkMinutes": 15}, {"price": 2100, "area": 75.0, "unitPrice": 28.0, "buildingYear": 1984, "age": 41, "floorPlan": "３ＬＤＫ＋Ｓ", "structure": "ＳＲＣ", "district": "祐光", "period": "2024年第4四半期", "walkMinutes": 3}, {"price": 1800, "area": 65.0, "unitPrice": 27.69, "buildingYear": 1989, "age": 36, "floorPlan": "３ＬＤＫ", "structure": "ＲＣ", "district": "道場北", "period": "2024年第4四半期", "walkMinutes": 10}, {"price": 1300, "area": 75.0, "unitPrice": 17.33, "buildingYear": 1989, "age": 36, "floorPlan": "２ＬＤＫ", "structure": "ＲＣ", "district": "道場北", "period": "2024年第4四半期", "walkMinutes": 14}, {"price": 450, "area": 15.0, "unitPrice": 30.0, "buildingYear": 1989, "age": 36, "floorPlan": "１Ｋ", "structure": "ＲＣ", "district": "要町", "period": "2024年第4四半期", "walkMinutes": 1}, {"price": 1300, "area": 70.0, "unitPrice": 18.57, "buildingYear": 1989, "age": 36, "floorPlan": "２ＬＤＫ", "structure": "", "district": "道場北", "period": "2024年第4四半期", "walkMinutes": 14}, {"price": 2400, "area": 70.0, "unitPrice": 34.29, "buildingYear": 2001, "age": 24, "floorPlan": "３ＬＤＫ", "structure": "ＲＣ", "district": "祐光", "period": "2024年第4四半期", "walkMinutes": 8}]