[{"price": 3700, "area": 70.0, "unitPrice": 52.86, "buildingYear": 2007, "age": 18, "floorPlan": "２ＬＤＫ", "structure": "ＲＣ", "district": "西船", "period": "2025年第2四半期", "walkMinutes": 6}, {"price": 3700, "area": 70.0, "unitPrice": 52.86, "buildingYear": 2006, "age": 19, "floorPlan": "２ＬＤＫ", "structure": "ＲＣ", "district": "印内", "period": "2025年第2四半期", "walkMinutes": 6}, {"price": 2100, "area": 85.0, "unitPrice": 24.71, "buildingYear": null, "age": null, "floorPlan": "４ＬＤＫ", "structure": "", "district": "印内", "period": "2025年第2四半期", "walkMinutes": 8}, {"price": 3000, "area": 70.0, "unitPrice": 42.86, "buildingYear": 2012, "age": 13, "floorPlan": "２ＬＤＫ＋Ｓ", "structure": "ＲＣ", "district": "西船", "period": "2025年第1四半期", "walkMinutes": 10}, {"price": 2900, "area": 75.0, "unitPrice": 38.67, "buildingYear": 2005, "age": 20, "floorPlan": "３ＬＤＫ", "structure": "ＲＣ", "district": "印内", "period": "2025年第1四半期", "walkMinutes": 13}, {"price": 3700, "area": 75.0, "unitPrice": 49.33, "buildingYear": 2001, "age": 24, "floorPlan": "３ＬＤＫ", "structure": "ＲＣ", "district": "印内", "period": "2024年第4四半期", "walkMinutes": 11}]