[{"price": 3800, "area": 85.0, "unitPrice": 44.71, "buildingYear": 1997, "age": 28, "floorPlan": "３ＬＤＫ", "structure": "ＲＣ", "district": "上町屋", "period": "2025年第3四半期", "walkMinutes": 3}, {"price": 3700, "area": 65.0, "unitPrice": 56.92, "buildingYear": 1998, "age": 27, "floorPlan": "２ＬＤＫ", "structure": "ＲＣ", "district": "寺分", "period": "2025年第2四半期", "walkMinutes": 3}, {"price": 3100, "area": 80.0, "unitPrice": 38.75, "buildingYear": 1998, "age": 27, "floorPlan": "３ＬＤＫ", "structure": "ＲＣ", "district": "寺分", "period": "2025年第2四半期", "walkMinutes": 4}, {"price": 4500, "area": 100.0, "unitPrice": 45.0, "buildingYear": 1997, "age": 28, "floorPlan": "４ＬＤＫ", "structure": "ＲＣ", "district": "上町屋", "period": "2025年第2四半期", "walkMinutes": 3}, {"price": 4000, "area": 85.0, "unitPrice": 47.06, "buildingYear": 1997, "age": 28, "floorPlan": "４ＬＤＫ", "structure": "ＲＣ", "district": "上町屋", "period": "2025年第2四半期", "walkMinutes": 4}]