[{"price": 2300, "area": 115.0, "unitPrice": 20.0, "buildingYear": 2008, "age": 17, "floorPlan": "４ＬＤＫ", "structure": "ＲＣ", "district": "末広", "period": "2025年第3四半期", "walkMinutes": 23}, {"price": 630, "area": 65.0, "unitPrice": 9.69, "buildingYear": 1981, "age": 44, "floorPlan": "３ＬＤＫ", "structure": "ＲＣ", "district": "泉", "period": "2025年第3四半期", "walkMinutes": 14}, {"price": 2200, "area": 85.0, "unitPrice": 25.88, "buildingYear": 1984, "age": 41, "floorPlan": "３ＬＤＫ", "structure": "ＲＣ", "district": "若宮", "period": "2025年第3四半期", "walkMinutes": 3}, {"price": 3200, "area": 75.0, "unitPrice": 42.67, "buildingYear": 2002, "age": 23, "floorPlan": "４ＬＤＫ", "structure": "ＳＲＣ", "district": "鴨川", "period": "2025年第3四半期", "walkMinutes": 14}, {"price": 2400, "area": 65.0, "unitPrice": 36.92, "buildingYear": 2005, "age": 20, "floorPlan": "３ＬＤＫ", "structure": "ＲＣ", "district": "朝日", "period": "2025年第2四半期", "walkMinutes": 8}, {"price": 3300, "area": 75.0, "unitPrice": 44.0, "buildingYear": 2005, "age": 20, "floorPlan": "３ＬＤＫ", "structure": "ＲＣ", "district": "朝日", "period": "2025年第2四半期", "walkMinutes": 8}, {"price": 1400, "area": 80.0, "unitPrice": 17.5, "buildingYear": 1992, "age": 33, "floorPlan": "３ＬＤＫ", "structure": "ＲＣ", "district": "西", "period": "2025年第2四半期", "walkMinutes": 17}, {"price": 2200, "area": 70.0, "unitPrice": 31.43, "buildingYear": 2004, "age": 21, "floorPlan": "３ＬＤＫ", "structure": "ＲＣ", "district": "西", "period": "2025年第2四半期", "walkMinutes": 15}, {"price": 3300, "area": 70.0, "unitPrice": 47.14, "buildingYear": 2005, "age": 20, "floorPlan": "３ＬＤＫ", "structure": "ＲＣ", "district": "朝日", "period": "2025年第2四半期", "walkMinutes": 10}, {"price": 320, "area": 65.0, "unitPrice": 4.92, "buildingYear": 1981, "age": 44, "floorPlan": "３ＬＤＫ", "structure": "ＲＣ", "district": "泉", "period": "2025年第2四半期", "walkMinutes": 14}, {"price": 200, "area": 65.0, "unitPrice": 3.08, "buildingYear": 1981, "age": 44, "floorPlan": "３ＬＤＫ", "structure": "ＲＣ", "district": "泉", "period": "2025年第2四半期", "walkMinutes": 15}, {"price": 1800, "area": 50.0, "unitPrice": 36.0, "buildingYear": 1989, "age": 36, "floorPlan": "３ＬＤＫ", "structure": "ＲＣ", "district": "南", "period": "2025年第2四半期", "walkMinutes": 9}, {"price": 1200, "area": 75.0, "unitPrice": 16.0, "buildingYear": 1984, "age": 41, "floorPlan": "３ＬＤＫ", "structure": "ＲＣ", "district": "若宮", "period": "2025年第2四半期", "walkMinutes": 4}, {"price": 2200, "area": 90.0, "unitPrice": 24.44, "buildingYear": 2002, "age": 23, "floorPlan": "４ＬＤＫ", "structure": "ＳＲＣ", "district": "鴨川", "period": "2025年第1四半期", "walkMinutes": 12}, {"price": 2600, "area": 75.0, "unitPrice": 34.67, "buildingYear": 2005, "age": 20, "floorPlan": "３ＬＤＫ", "structure": "ＲＣ", "district": "朝日", "period": "2025年第1四半期", "walkMinutes": 8}, {"price": 1800, "area": 60.0, "unitPrice": 30.0, "buildingYear": 2000, "age": 25, "floorPlan": "２ＬＤＫ＋Ｓ", "structure": "ＲＣ", "district": "東", "period": "2025年第1四半期", "walkMinutes": 4}, {"price": 2600, "area": 70.0, "unitPrice": 37.14, "buildingYear": 2005, "age": 20, "floorPlan": "３ＬＤＫ", "structure": "ＲＣ", "district": "朝日", "period": "2025年第1四半期", "walkMinutes": 10}, {"price": 1200, "area": 60.0, "unitPrice": 20.0, "buildingYear": 1993, "age": 32, "floorPlan": "３ＬＤＫ", "structure": "ＲＣ", "district": "末広", "period": "2025年第1四半期", "walkMinutes": 12}, {"price": 1500, "area": 65.0, "unitPrice": 23.08, "buildingYear": 2007, "age": 18, "floorPlan": "３ＬＤＫ", "structure": "ＲＣ", "district": "二ツ家", "period": "2025年第1四半期", "walkMinutes": null}, {"price": 2600, "area": 80.0, "unitPrice": 32.5, "buildingYear": 2005, "age": 20, "floorPlan": "４ＬＤＫ", "structure": "ＲＣ", "district": "朝日", "period": "2024年第4四半期", "walkMinutes": 9}, {"price": 1300, "area": 80.0, "unitPrice": 16.25, "buildingYear": 1984, "age": 41, "floorPlan": "３ＬＤＫ", "structure": "ＲＣ", "district": "若宮", "period": "2024年第4四半期", "walkMinutes": 3}, {"price": 900, "area": 65.0, "unitPrice": 13.85, "buildingYear": 1981, "age": 44, "floorPlan": "３ＬＤＫ", "structure": "ＲＣ", "district": "泉", "period": "2024年第4四半期", "walkMinutes": 15}, {"price": 1500, "area": 50.0, "unitPrice": 30.0, "buildingYear": 1989, "age": 36, "floorPlan": "３ＬＤＫ", "structure": "ＲＣ", "district": "南", "period": "2024年第4四半期", "walkMinutes": 9}, {"price": 320, "area": 15.0, "unitPrice": 21.33, "buildingYear": 1991, "age": 34, "floorPlan": "１Ｋ", "structure": "ＲＣ", "district": "若宮", "period": "2024年第4四半期", "walkMinutes": 7}, {"price": 1000, "area": 85.0, "unitPrice": 11.76, "buildingYear": 1992, "age": 33, "floorPlan": "３ＬＤＫ", "structure": "ＳＲＣ", "district": "二ツ家", "period": "2024年第4四半期", "walkMinutes": null}]