[{"price": 8600, "area": 80.0, "unitPrice": 107.5, "buildingYear": 2004, "age": 21, "floorPlan": "３ＬＤＫ", "structure": "ＲＣ", "district": "境", "period": "2025年第3四半期", "walkMinutes": 11}, {"price": 2500, "area": 60.0, "unitPrice": 41.67, "buildingYear": 1971, "age": 54, "floorPlan": "２ＬＤＫ", "structure": "ＲＣ", "district": "境", "period": "2025年第3四半期", "walkMinutes": 5}, {"price": 4500, "area": 70.0, "unitPrice": 64.29, "buildingYear": 2003, "age": 22, "floorPlan": "２ＬＤＫ", "structure": "ＲＣ", "district": "境南町", "period": "2025年第3四半期", "walkMinutes": 7}, {"price": 5500, "area": 60.0, "unitPrice": 91.67, "buildingYear": 2003, "age": 22, "floorPlan": "２ＬＤＫ", "structure": "ＲＣ", "district": "境南町", "period": "2025年第3四半期", "walkMinutes": 7}, {"price": 7000, "area": 55.0, "unitPrice": 127.27, "buildingYear": 2022, "age": 3, "floorPlan": "２ＬＤＫ", "structure": "ＲＣ", "district": "境南町", "period": "2025年第3四半期", "walkMinutes": 6}, {"price": 8900, "area": 60.0, "unitPrice": 148.33, "buildingYear": 2013, "age": 12, "floorPlan": "２ＬＤＫ", "structure": "ＲＣ", "district": "境南町", "period": "2025年第3四半期", "walkMinutes": 2}, {"price": 6100, "area": 85.0, "unitPrice": 71.76, "buildingYear": 2003, "age": 22, "floorPlan": "２ＬＤＫ＋Ｓ", "structure": "ＲＣ", "district": "境南町", "period": "2025年第3四半期", "walkMinutes": 7}, {"price": 1300, "area": 40.0, "unitPrice": 32.5, "buildingYear": 1969, "age": 56, "floorPlan": "２ＤＫ", "structure": "ＲＣ", "district": "境南町", "period": "2025年第3四半期", "walkMinutes": 9}, {"price": 3500, "area": 25.0, "unitPrice": 140.0, "buildingYear": 2024, "age": 1, "floorPlan": "１Ｋ", "structure": "ＲＣ", "district": "境", "period": "2025年第3四半期", "walkMinutes": 11}, {"price": 4000, "area": 85.0, "unitPrice": 47.06, "buildingYear": 1999, "age": 26, "floorPlan": "３ＬＤＫ", "structure": "ＲＣ", "district": "深大寺", "period": "2025年第3四半期", "walkMinutes": 25}, {"price": 7500, "area": 85.0, "unitPrice": 88.24, "buildingYear": 2007, "age": 18, "floorPlan": "４ＬＤＫ", "structure": "ＲＣ", "district": "井口", "period": "2025年第3四半期", "walkMinutes": 11}, {"price": 6500, "area": 80.0, "unitPrice": 81.25, "buildingYear": 2007, "age": 18, "floorPlan": "３ＬＤＫ", "structure": "ＲＣ", "district": "井口", "period": "2025年第3四半期", "walkMinutes": 18}, {"price": 3800, "area": 60.0, "unitPrice": 63.33, "buildingYear": 1995, "age": 30, "floorPlan": "３ＤＫ", "structure": "ＲＣ", "district": "井口", "period": "2025年第3四半期", "walkMinutes": 13}, {"price": 4000, "area": 55.0, "unitPrice": 72.73, "buildingYear": 1999, "age": 26, "floorPlan": "２ＬＤＫ", "structure": "ＲＣ", "district": "野崎", "period": "2025年第3四半期", "walkMinutes": 29}, {"price": 3800, "area": 65.0, "unitPrice": 58.46, "buildingYear": 2010, "age": 15, "floorPlan": "３ＬＤＫ", "structure": "ＲＣ", "district": "新町", "period": "2025年第3四半期", "walkMinutes": 17}, {"price": 8500, "area": 75.0, "unitPrice": 113.33, "buildingYear": 2020, "age": 5, "floorPlan": "３ＬＤＫ", "structure": "ＲＣ", "district": "境", "period": "2025年第2四半期", "walkMinutes": 9}, {"price": 4800, "area": 70.0, "unitPrice": 68.57, "buildingYear": 1980, "age": 45, "floorPlan": "３ＬＤＫ", "structure": "ＲＣ", "district": "境", "period": "2025年第2四半期", "walkMinutes": 12}, {"price": 4000, "area": 35.0, "unitPrice": 114.29, "buildingYear": 2005, "age": 20, "floorPlan": "１ＤＫ", "structure": "ＳＲＣ", "district": "境", "period": "2025年第2四半期", "walkMinutes": 2}, {"price": 9500, "area": 80.0, "unitPrice": 118.75, "buildingYear": 2009, "age": 16, "floorPlan": "３ＬＤＫ", "structure": "ＲＣ", "district": "境", "period": "2025年第2四半期", "walkMinutes": 10}, {"price": 7200, "area": 85.0, "unitPrice": 84.71, "buildingYear": 2012, "age": 13, "floorPlan": "３ＬＤＫ", "structure": "ＲＣ", "district": "桜堤", "period": "2025年第2四半期", "walkMinutes": null}, {"price": 5900, "area": 75.0, "unitPrice": 78.67, "buildingYear": 2012, "age": 13, "floorPlan": "３ＬＤＫ", "structure": "ＲＣ", "district": "桜堤", "period": "2025年第2四半期", "walkMinutes": null}, {"price": 6900, "area": 85.0, "unitPrice": 81.18, "buildingYear": 2012, "age": 13, "floorPlan": "３ＬＤＫ", "structure": "ＲＣ", "district": "桜堤", "period": "2025年第2四半期", "walkMinutes": null}, {"price": 3800, "area": 65.0, "unitPrice": 58.46, "buildingYear": 1990, "age": 35, "floorPlan": "２ＤＫ", "structure": "ＲＣ", "district": "境南町", "period": "2025年第2四半期", "walkMinutes": 3}, {"price": 2800, "area": 60.0, "unitPrice": 46.67, "buildingYear": 1973, "age": 52, "floorPlan": "３ＬＤＫ", "structure": "ＲＣ", "district": "境南町", "period": "2025年第2四半期", "walkMinutes": 7}, {"price": 4500, "area": 70.0, "unitPrice": 64.29, "buildingYear": 1978, "age": 47, "floorPlan": "２ＬＤＫ", "structure": "ＳＲＣ", "district": "境南町", "period": "2025年第2四半期", "walkMinutes": 5}, {"price": 1800, "area": 40.0, "unitPrice": 45.0, "buildingYear": 1983, "age": 42, "floorPlan": "１ＬＤＫ", "structure": "ＲＣ", "district": "境南町", "period": "2025年第2四半期", "walkMinutes": 10}, {"price": 4300, "area": 70.0, "unitPrice": 61.43, "buildingYear": 1977, "age": 48, "floorPlan": "３ＤＫ", "structure": "ＳＲＣ", "district": "境南町", "period": "2025年第2四半期", "walkMinutes": 5}, {"price": 1600, "area": 70.0, "unitPrice": 22.86, "buildingYear": 1978, "age": 47, "floorPlan": "４Ｋ", "structure": "ＲＣ", "district": "境南町", "period": "2025年第2四半期", "walkMinutes": 4}, {"price": 9100, "area": 75.0, "unitPrice": 121.33, "buildingYear": 2021, "age": 4, "floorPlan": "２ＬＤＫ＋Ｓ", "structure": "ＲＣ", "district": "境南町", "period": "2025年第2四半期", "walkMinutes": 9}, {"price": 1300, "area": 45.0, "unitPrice": 28.89, "buildingYear": 1969, "age": 56, "floorPlan": "１ＤＫ＋Ｓ", "structure": "ＲＣ", "district": "境南町", "period": "2025年第2四半期", "walkMinutes": 10}, {"price": 1100, "area": 20.0, "unitPrice": 55.0, "buildingYear": 1985, "age": 40, "floorPlan": "１Ｒ", "structure": "ＲＣ", "district": "境南町", "period": "2025年第2四半期", "walkMinutes": 7}, {"price": 6600, "area": 80.0, "unitPrice": 82.5, "buildingYear": 1995, "age": 30, "floorPlan": "３ＬＤＫ", "structure": "ＲＣ", "district": "境", "period": "2025年第2四半期", "walkMinutes": 3}, {"price": 7200, "area": 80.0, "unitPrice": 90.0, "buildingYear": 2012, "age": 13, "floorPlan": "３ＬＤＫ", "structure": "ＲＣ", "district": "桜堤", "period": "2025年第2四半期", "walkMinutes": 25}, {"price": 2400, "area": 60.0, "unitPrice": 40.0, "buildingYear": null, "age": null, "floorPlan": "", "structure": "ＳＲＣ", "district": "関前", "period": "2025年第2四半期", "walkMinutes": 23}, {"price": 6500, "area": 65.0, "unitPrice": 100.0, "buildingYear": 2020, "age": 5, "floorPlan": "３ＬＤＫ", "structure": "ＲＣ", "district": "井口", "period": "2025年第2四半期", "walkMinutes": 12}, {"price": 3800, "area": 65.0, "unitPrice": 58.46, "buildingYear": 2011, "age": 14, "floorPlan": "３ＬＤＫ", "structure": "ＲＣ", "district": "新町", "period": "2025年第2四半期", "walkMinutes": null}, {"price": 10000, "area": 120.0, "unitPrice": 83.33, "buildingYear": 1995, "age": 30, "floorPlan": "３ＬＤＫ", "structure": "ＲＣ", "district": "境", "period": "2025年第1四半期", "walkMinutes": 3}, {"price": 8800, "area": 70.0, "unitPrice": 125.71, "buildingYear": 2013, "age": 12, "floorPlan": "３ＬＤＫ", "structure": "ＲＣ", "district": "境", "period": "2025年第1四半期", "walkMinutes": 2}, {"price": 3500, "area": 70.0, "unitPrice": 50.0, "buildingYear": 1979, "age": 46, "floorPlan": "２ＬＤＫ", "structure": "ＲＣ", "district": "境", "period": "2025年第1四半期", "walkMinutes": 7}, {"price": 8500, "area": 85.0, "unitPrice": 100.0, "buildingYear": 2009, "age": 16, "floorPlan": "３ＬＤＫ", "structure": "ＲＣ", "district": "境", "period": "2025年第1四半期", "walkMinutes": 9}, {"price": 6300, "area": 80.0, "unitPrice": 78.75, "buildingYear": 2012, "age": 13, "floorPlan": "３ＬＤＫ", "structure": "ＲＣ", "district": "桜堤", "period": "2025年第1四半期", "walkMinutes": null}, {"price": 6600, "area": 80.0, "unitPrice": 82.5, "buildingYear": 2012, "age": 13, "floorPlan": "３ＬＤＫ", "structure": "ＲＣ", "district": "桜堤", "period": "2025年第1四半期", "walkMinutes": null}, {"price": 6300, "area": 80.0, "unitPrice": 78.75, "buildingYear": 2012, "age": 13, "floorPlan": "３ＬＤＫ", "structure": "ＲＣ", "district": "桜堤", "period": "2025年第1四半期", "walkMinutes": null}, {"price": 6800, "area": 90.0, "unitPrice": 75.56, "buildingYear": 2012, "age": 13, "floorPlan": "３ＬＤＫ", "structure": "ＲＣ", "district": "桜堤", "period": "2025年第1四半期", "walkMinutes": null}, {"price": 7300, "area": 80.0, "unitPrice": 91.25, "buildingYear": 2012, "age": 13, "floorPlan": "３ＬＤＫ", "structure": "ＲＣ", "district": "桜堤", "period": "2025年第1四半期", "walkMinutes": null}, {"price": 7000, "area": 80.0, "unitPrice": 87.5, "buildingYear": 2013, "age": 12, "floorPlan": "３ＬＤＫ", "structure": "ＲＣ", "district": "桜堤", "period": "2025年第1四半期", "walkMinutes": null}, {"price": 6200, "area": 75.0, "unitPrice": 82.67, "buildingYear": 2015, "age": 10, "floorPlan": "３ＬＤＫ", "structure": "ＲＣ", "district": "境南町", "period": "2025年第1四半期", "walkMinutes": 4}, {"price": 1200, "area": 30.0, "unitPrice": 40.0, "buildingYear": 1982, "age": 43, "floorPlan": "１Ｒ", "structure": "ＳＲＣ", "district": "境南町", "period": "2025年第1四半期", "walkMinutes": 4}, {"price": 4900, "area": 55.0, "unitPrice": 89.09, "buildingYear": 2006, "age": 19, "floorPlan": "１ＬＤＫ＋Ｓ", "structure": "ＲＣ", "district": "境南町", "period": "2025年第1四半期", "walkMinutes": 7}, {"price": 8600, "area": 70.0, "unitPrice": 122.86, "buildingYear": 2019, "age": 6, "floorPlan": "３ＬＤＫ", "structure": "ＲＣ", "district": "境南町", "period": "2025年第1四半期", "walkMinutes": 7}, {"price": 8500, "area": 125.0, "unitPrice": 68.0, "buildingYear": 1983, "age": 42, "floorPlan": "４ＬＤＫ＋Ｓ", "structure": "ＲＣ", "district": "境南町", "period": "2025年第1四半期", "walkMinutes": 12}, {"price": 5200, "area": 70.0, "unitPrice": 74.29, "buildingYear": 1994, "age": 31, "floorPlan": "３ＬＤＫ", "structure": "ＲＣ", "district": "境南町", "period": "2025年第1四半期", "walkMinutes": 9}, {"price": 4200, "area": 70.0, "unitPrice": 60.0, "buildingYear": 1968, "age": 57, "floorPlan": "３ＬＤＫ", "structure": "ＲＣ", "district": "境南町", "period": "2025年第1四半期", "walkMinutes": 10}, {"price": 4700, "area": 65.0, "unitPrice": 72.31, "buildingYear": 2011, "age": 14, "floorPlan": "１ＬＤＫ＋Ｓ", "structure": "ＲＣ", "district": "境南町", "period": "2025年第1四半期", "walkMinutes": 14}, {"price": 3300, "area": 55.0, "unitPrice": 60.0, "buildingYear": 1973, "age": 52, "floorPlan": "２ＬＤＫ", "structure": "ＲＣ", "district": "境南町", "period": "2025年第1四半期", "walkMinutes": 7}, {"price": 4400, "area": 60.0, "unitPrice": 73.33, "buildingYear": 1977, "age": 48, "floorPlan": "", "structure": "ＳＲＣ", "district": "境南町", "period": "2025年第1四半期", "walkMinutes": 7}, {"price": 8500, "area": 65.0, "unitPrice": 130.77, "buildingYear": 2013, "age": 12, "floorPlan": "３ＬＤＫ", "structure": "ＲＣ", "district": "境", "period": "2025年第1四半期", "walkMinutes": 2}, {"price": 5400, "area": 80.0, "unitPrice": 67.5, "buildingYear": 2001, "age": 24, "floorPlan": "３ＬＤＫ", "structure": "ＲＣ", "district": "桜堤", "period": "2025年第1四半期", "walkMinutes": 18}, {"price": 7000, "area": 70.0, "unitPrice": 100.0, "buildingYear": 2013, "age": 12, "floorPlan": "３ＬＤＫ", "structure": "ＲＣ", "district": "桜堤", "period": "2025年第1四半期", "walkMinutes": 21}, {"price": 5900, "area": 65.0, "unitPrice": 90.77, "buildingYear": 2021, "age": 4, "floorPlan": "３ＬＤＫ", "structure": "ＲＣ", "district": "上連雀", "period": "2025年第1四半期", "walkMinutes": 19}, {"price": 4200, "area": 90.0, "unitPrice": 46.67, "buildingYear": 2001, "age": 24, "floorPlan": "３ＬＤＫ", "structure": "ＲＣ", "district": "井口", "period": "2025年第1四半期", "walkMinutes": 20}, {"price": 4400, "area": 110.0, "unitPrice": 40.0, "buildingYear": 2001, "age": 24, "floorPlan": "４ＬＤＫ", "structure": "ＲＣ", "district": "井口", "period": "2025年第1四半期", "walkMinutes": 22}, {"price": 4300, "area": 90.0, "unitPrice": 47.78, "buildingYear": 2001, "age": 24, "floorPlan": "３ＬＤＫ", "structure": "ＲＣ", "district": "井口", "period": "2025年第1四半期", "walkMinutes": 22}, {"price": 5900, "area": 80.0, "unitPrice": 73.75, "buildingYear": 2011, "age": 14, "floorPlan": "３ＬＤＫ", "structure": "ＲＣ", "district": "井口", "period": "2025年第1四半期", "walkMinutes": null}, {"price": 4200, "area": 25.0, "unitPrice": 168.0, "buildingYear": 2001, "age": 24, "floorPlan": "３ＬＤＫ", "structure": "ＲＣ", "district": "井口", "period": "2025年第1四半期", "walkMinutes": 23}, {"price": 4800, "area": 80.0, "unitPrice": 60.0, "buildingYear": 1999, "age": 26, "floorPlan": "４ＬＤＫ", "structure": "ＲＣ", "district": "深大寺", "period": "2025年第1四半期", "walkMinutes": 25}, {"price": 4200, "area": 65.0, "unitPrice": 64.62, "buildingYear": 2010, "age": 15, "floorPlan": "３ＬＤＫ", "structure": "ＲＣ", "district": "新町", "period": "2025年第1四半期", "walkMinutes": 18}, {"price": 4200, "area": 55.0, "unitPrice": 76.36, "buildingYear": 2010, "age": 15, "floorPlan": "３ＬＤＫ", "structure": "ＲＣ", "district": "新町", "period": "2025年第1四半期", "walkMinutes": 18}, {"price": 7400, "area": 70.0, "unitPrice": 105.71, "buildingYear": 2020, "age": 5, "floorPlan": "３ＬＤＫ", "structure": "ＲＣ", "district": "境", "period": "2024年第4四半期", "walkMinutes": 9}, {"price": 7200, "area": 60.0, "unitPrice": 120.0, "buildingYear": 2020, "age": 5, "floorPlan": "２ＬＤＫ", "structure": "ＲＣ", "district": "境", "period": "2024年第4四半期", "walkMinutes": 9}, {"price": 5800, "area": 70.0, "unitPrice": 82.86, "buildingYear": 2009, "age": 16, "floorPlan": "２ＬＤＫ", "structure": "ＲＣ", "district": "境", "period": "2024年第4四半期", "walkMinutes": 10}, {"price": 6700, "area": 80.0, "unitPrice": 83.75, "buildingYear": 2012, "age": 13, "floorPlan": "３ＬＤＫ", "structure": "ＲＣ", "district": "桜堤", "period": "2024年第4四半期", "walkMinutes": null}, {"price": 5600, "area": 75.0, "unitPrice": 74.67, "buildingYear": 2013, "age": 12, "floorPlan": "３ＬＤＫ", "structure": "ＲＣ", "district": "桜堤", "period": "2024年第4四半期", "walkMinutes": null}, {"price": 6100, "area": 80.0, "unitPrice": 76.25, "buildingYear": 2012, "age": 13, "floorPlan": "３ＬＤＫ", "structure": "ＲＣ", "district": "桜堤", "period": "2024年第4四半期", "walkMinutes": null}, {"price": 6800, "area": 80.0, "unitPrice": 85.0, "buildingYear": 2013, "age": 12, "floorPlan": "３ＬＤＫ", "structure": "ＲＣ", "district": "桜堤", "period": "2024年第4四半期", "walkMinutes": 21}, {"price": 7800, "area": 100.0, "unitPrice": 78.0, "buildingYear": 2012, "age": 13, "floorPlan": "４ＬＤＫ", "structure": "ＲＣ", "district": "桜堤", "period": "2024年第4四半期", "walkMinutes": null}, {"price": 7000, "area": 60.0, "unitPrice": 116.67, "buildingYear": 2022, "age": 3, "floorPlan": "２ＬＤＫ＋Ｓ", "structure": "ＲＣ", "district": "境南町", "period": "2024年第4四半期", "walkMinutes": 6}, {"price": 2500, "area": 45.0, "unitPrice": 55.56, "buildingYear": 1969, "age": 56, "floorPlan": "１ＬＤＫ", "structure": "ＳＲＣ", "district": "境南町", "period": "2024年第4四半期", "walkMinutes": 3}, {"price": 1000, "area": 40.0, "unitPrice": 25.0, "buildingYear": 1978, "age": 47, "floorPlan": "２ＤＫ", "structure": "ＲＣ", "district": "境南町", "period": "2024年第4四半期", "walkMinutes": 11}, {"price": 860, "area": 20.0, "unitPrice": 43.0, "buildingYear": 1985, "age": 40, "floorPlan": "１Ｒ", "structure": "ＳＲＣ", "district": "境南町", "period": "2024年第4四半期", "walkMinutes": 1}, {"price": 3400, "area": 70.0, "unitPrice": 48.57, "buildingYear": 1983, "age": 42, "floorPlan": "２ＬＤＫ", "structure": "ＲＣ", "district": "境南町", "period": "2024年第4四半期", "walkMinutes": 13}, {"price": 7000, "area": 80.0, "unitPrice": 87.5, "buildingYear": 2000, "age": 25, "floorPlan": "３ＬＤＫ", "structure": "ＲＣ", "district": "境南町", "period": "2024年第4四半期", "walkMinutes": 7}, {"price": 5900, "area": 70.0, "unitPrice": 84.29, "buildingYear": 2017, "age": 8, "floorPlan": "２ＬＤＫ＋Ｓ", "structure": "ＲＣ", "district": "境南町", "period": "2024年第4四半期", "walkMinutes": 14}, {"price": 4900, "area": 55.0, "unitPrice": 89.09, "buildingYear": 2006, "age": 19, "floorPlan": "２ＬＤＫ", "structure": "ＲＣ", "district": "境南町", "period": "2024年第4四半期", "walkMinutes": 7}, {"price": 9200, "area": 70.0, "unitPrice": 131.43, "buildingYear": 2013, "age": 12, "floorPlan": "３ＬＤＫ", "structure": "ＲＣ", "district": "境南町", "period": "2024年第4四半期", "walkMinutes": 2}, {"price": 4400, "area": 65.0, "unitPrice": 67.69, "buildingYear": 1977, "age": 48, "floorPlan": "２ＬＤＫ", "structure": "ＳＲＣ", "district": "境南町", "period": "2024年第4四半期", "walkMinutes": 5}, {"price": 3700, "area": 80.0, "unitPrice": 46.25, "buildingYear": 1968, "age": 57, "floorPlan": "２ＬＤＫ＋Ｓ", "structure": "ＲＣ", "district": "境南町", "period": "2024年第4四半期", "walkMinutes": 11}, {"price": 2300, "area": 40.0, "unitPrice": 57.5, "buildingYear": 1969, "age": 56, "floorPlan": "２ＤＫ", "structure": "ＲＣ", "district": "境南町", "period": "2024年第4四半期", "walkMinutes": 9}, {"price": 4900, "area": 50.0, "unitPrice": 98.0, "buildingYear": 2006, "age": 19, "floorPlan": "２ＬＤＫ", "structure": "ＲＣ", "district": "境南町", "period": "2024年第4四半期", "walkMinutes": 6}, {"price": 7400, "area": 65.0, "unitPrice": 113.85, "buildingYear": 2020, "age": 5, "floorPlan": "３ＬＤＫ", "structure": "ＲＣ", "district": "境", "period": "2024年第4四半期", "walkMinutes": 10}, {"price": 5300, "area": 85.0, "unitPrice": 62.35, "buildingYear": 1989, "age": 36, "floorPlan": "４ＬＤＫ", "structure": "ＳＲＣ", "district": "八幡町", "period": "2024年第4四半期", "walkMinutes": 26}, {"price": 5300, "area": 80.0, "unitPrice": 66.25, "buildingYear": 2001, "age": 24, "floorPlan": "３ＬＤＫ", "structure": "ＲＣ", "district": "深大寺", "period": "2024年第4四半期", "walkMinutes": 18}, {"price": 4200, "area": 60.0, "unitPrice": 70.0, "buildingYear": 2007, "age": 18, "floorPlan": "２ＬＤＫ", "structure": "ＲＣ", "district": "井口", "period": "2024年第4四半期", "walkMinutes": 18}, {"price": 7200, "area": 85.0, "unitPrice": 84.71, "buildingYear": 2007, "age": 18, "floorPlan": "４ＬＤＫ", "structure": "ＲＣ", "district": "井口", "period": "2024年第4四半期", "walkMinutes": 11}, {"price": 2900, "area": 65.0, "unitPrice": 44.62, "buildingYear": 1974, "age": 51, "floorPlan": "２ＬＤＫ", "structure": "ＲＣ", "district": "井口", "period": "2024年第4四半期", "walkMinutes": 11}, {"price": 5800, "area": 75.0, "unitPrice": 77.33, "buildingYear": 2012, "age": 13, "floorPlan": "３ＬＤＫ", "structure": "ＲＣ", "district": "桜堤", "period": "2024年第3四半期", "walkMinutes": null}, {"price": 3000, "area": 75.0, "unitPrice": 40.0, "buildingYear": 1968, "age": 57, "floorPlan": "３ＬＤＫ", "structure": "ＲＣ", "district": "境南町", "period": "2024年第3四半期", "walkMinutes": 10}, {"price": 1100, "area": 30.0, "unitPrice": 36.67, "buildingYear": 1984, "age": 41, "floorPlan": "２ＤＫ", "structure": "ＲＣ", "district": "境南町", "period": "2024年第3四半期", "walkMinutes": 4}, {"price": 4000, "area": 65.0, "unitPrice": 61.54, "buildingYear": 1978, "age": 47, "floorPlan": "３ＬＤＫ", "structure": "ＳＲＣ", "district": "境南町", "period": "2024年第3四半期", "walkMinutes": 6}, {"price": 7000, "area": 60.0, "unitPrice": 116.67, "buildingYear": 2022, "age": 3, "floorPlan": "３ＬＤＫ", "structure": "ＲＣ", "district": "境南町", "period": "2024年第3四半期", "walkMinutes": 6}, {"price": 2900, "area": 45.0, "unitPrice": 64.44, "buildingYear": 1977, "age": 48, "floorPlan": "１ＤＫ", "structure": "ＳＲＣ", "district": "境南町", "period": "2024年第3四半期", "walkMinutes": 7}, {"price": 5600, "area": 65.0, "unitPrice": 86.15, "buildingYear": 1996, "age": 29, "floorPlan": "３ＬＤＫ", "structure": "ＲＣ", "district": "境南町", "period": "2024年第3四半期", "walkMinutes": 8}, {"price": 7000, "area": 55.0, "unitPrice": 127.27, "buildingYear": 2022, "age": 3, "floorPlan": "３ＬＤＫ", "structure": "ＲＣ", "district": "境南町", "period": "2024年第3四半期", "walkMinutes": 6}, {"price": 4000, "area": 55.0, "unitPrice": 72.73, "buildingYear": 1973, "age": 52, "floorPlan": "３ＬＤＫ", "structure": "ＲＣ", "district": "境南町", "period": "2024年第3四半期", "walkMinutes": 7}, {"price": 5000, "area": 80.0, "unitPrice": 62.5, "buildingYear": 1989, "age": 36, "floorPlan": "３ＬＤＫ", "structure": "ＲＣ", "district": "境南町", "period": "2024年第3四半期", "walkMinutes": 14}, {"price": 930, "area": 20.0, "unitPrice": 46.5, "buildingYear": 1984, "age": 41, "floorPlan": "１Ｋ", "structure": "ＲＣ", "district": "境", "period": "2024年第3四半期", "walkMinutes": 5}, {"price": 1300, "area": 15.0, "unitPrice": 86.67, "buildingYear": 2005, "age": 20, "floorPlan": "１Ｋ", "structure": "ＲＣ", "district": "関前", "period": "2024年第3四半期", "walkMinutes": 17}, {"price": 4400, "area": 75.0, "unitPrice": 58.67, "buildingYear": 1989, "age": 36, "floorPlan": "３ＬＤＫ", "structure": "ＳＲＣ", "district": "八幡町", "period": "2024年第3四半期", "walkMinutes": 26}, {"price": 8300, "area": 75.0, "unitPrice": 110.67, "buildingYear": 2018, "age": 7, "floorPlan": "３ＬＤＫ", "structure": "ＲＣ", "district": "上連雀", "period": "2024年第3四半期", "walkMinutes": 9}, {"price": 4700, "area": 75.0, "unitPrice": 62.67, "buildingYear": 2001, "age": 24, "floorPlan": "３ＬＤＫ", "structure": "ＲＣ", "district": "深大寺", "period": "2024年第3四半期", "walkMinutes": 18}, {"price": 2600, "area": 70.0, "unitPrice": 37.14, "buildingYear": 1974, "age": 51, "floorPlan": "３ＬＤＫ", "structure": "ＲＣ", "district": "井口", "period": "2024年第3四半期", "walkMinutes": 11}, {"price": 3600, "area": 65.0, "unitPrice": 55.38, "buildingYear": 1974, "age": 51, "floorPlan": "３ＬＤＫ", "structure": "ＲＣ", "district": "井口", "period": "2024年第3四半期", "walkMinutes": 11}, {"price": 6500, "area": 60.0, "unitPrice": 108.33, "buildingYear": 2020, "age": 5, "floorPlan": "２ＬＤＫ", "structure": "ＲＣ", "district": "井口", "period": "2024年第3四半期", "walkMinutes": 13}, {"price": 4700, "area": 65.0, "unitPrice": 72.31, "buildingYear": 2001, "age": 24, "floorPlan": "３ＬＤＫ", "structure": "ＲＣ", "district": "深大寺", "period": "2024年第3四半期", "walkMinutes": 20}, {"price": 4400, "area": 55.0, "unitPrice": 80.0, "buildingYear": 1987, "age": 38, "floorPlan": "１ＬＤＫ＋Ｓ", "structure": "ＲＣ", "district": "境", "period": "2024年第2四半期", "walkMinutes": 3}, {"price": 6600, "area": 80.0, "unitPrice": 82.5, "buildingYear": 2004, "age": 21, "floorPlan": "３ＬＤＫ", "structure": "ＲＣ", "district": "境", "period": "2024年第2四半期", "walkMinutes": 11}, {"price": 7200, "area": 80.0, "unitPrice": 90.0, "buildingYear": 2009, "age": 16, "floorPlan": "３ＬＤＫ", "structure": "ＲＣ", "district": "境", "period": "2024年第2四半期", "walkMinutes": 10}, {"price": 5700, "area": 75.0, "unitPrice": 76.0, "buildingYear": 2012, "age": 13, "floorPlan": "３ＬＤＫ", "structure": "ＲＣ", "district": "桜堤", "period": "2024年第2四半期", "walkMinutes": null}, {"price": 7400, "area": 95.0, "unitPrice": 77.89, "buildingYear": 2012, "age": 13, "floorPlan": "３ＬＤＫ", "structure": "ＲＣ", "district": "桜堤", "period": "2024年第2四半期", "walkMinutes": null}, {"price": 5200, "area": 65.0, "unitPrice": 80.0, "buildingYear": 1994, "age": 31, "floorPlan": "３ＬＤＫ", "structure": "ＲＣ", "district": "境南町", "period": "2024年第2四半期", "walkMinutes": 9}, {"price": 2900, "area": 55.0, "unitPrice": 52.73, "buildingYear": 1978, "age": 47, "floorPlan": "１ＬＤＫ", "structure": "ＲＣ", "district": "境南町", "period": "2024年第2四半期", "walkMinutes": 5}, {"price": 5200, "area": 90.0, "unitPrice": 57.78, "buildingYear": 1980, "age": 45, "floorPlan": "３ＬＤＫ", "structure": "ＲＣ", "district": "境南町", "period": "2024年第2四半期", "walkMinutes": 10}, {"price": 1500, "area": 35.0, "unitPrice": 42.86, "buildingYear": 1982, "age": 43, "floorPlan": "１ＤＫ", "structure": "ＳＲＣ", "district": "境南町", "period": "2024年第2四半期", "walkMinutes": 3}, {"price": 5600, "area": 70.0, "unitPrice": 80.0, "buildingYear": 1996, "age": 29, "floorPlan": "３ＬＤＫ", "structure": "ＲＣ", "district": "境南町", "period": "2024年第2四半期", "walkMinutes": 9}, {"price": 5700, "area": 45.0, "unitPrice": 126.67, "buildingYear": 2022, "age": 3, "floorPlan": "２ＬＤＫ", "structure": "ＲＣ", "district": "境南町", "period": "2024年第2四半期", "walkMinutes": 6}, {"price": 4400, "area": 65.0, "unitPrice": 67.69, "buildingYear": 1977, "age": 48, "floorPlan": "２ＬＤＫ", "structure": "ＳＲＣ", "district": "境南町", "period": "2024年第2四半期", "walkMinutes": 5}, {"price": 4700, "area": 65.0, "unitPrice": 72.31, "buildingYear": 1977, "age": 48, "floorPlan": "３ＬＤＫ", "structure": "ＳＲＣ", "district": "境南町", "period": "2024年第2四半期", "walkMinutes": 7}, {"price": 5700, "area": 40.0, "unitPrice": 142.5, "buildingYear": 2022, "age": 3, "floorPlan": "２ＬＤＫ", "structure": "ＲＣ", "district": "境南町", "period": "2024年第2四半期", "walkMinutes": 6}, {"price": 1000, "area": 20.0, "unitPrice": 50.0, "buildingYear": 1987, "age": 38, "floorPlan": "１Ｋ", "structure": "ＲＣ", "district": "境", "period": "2024年第2四半期", "walkMinutes": 6}, {"price": 4400, "area": 50.0, "unitPrice": 88.0, "buildingYear": 1986, "age": 39, "floorPlan": "１ＬＤＫ", "structure": "ＲＣ", "district": "境", "period": "2024年第2四半期", "walkMinutes": 3}, {"price": 4200, "area": 55.0, "unitPrice": 76.36, "buildingYear": 1998, "age": 27, "floorPlan": "２ＬＤＫ", "structure": "ＲＣ", "district": "桜堤", "period": "2024年第2四半期", "walkMinutes": 24}, {"price": 5700, "area": 70.0, "unitPrice": 81.43, "buildingYear": 2012, "age": 13, "floorPlan": "３ＬＤＫ", "structure": "ＲＣ", "district": "桜堤", "period": "2024年第2四半期", "walkMinutes": 23}, {"price": 7400, "area": 90.0, "unitPrice": 82.22, "buildingYear": 2012, "age": 13, "floorPlan": "４ＬＤＫ", "structure": "ＲＣ", "district": "桜堤", "period": "2024年第2四半期", "walkMinutes": 23}, {"price": 2400, "area": 45.0, "unitPrice": 53.33, "buildingYear": 1969, "age": 56, "floorPlan": "２ＬＤＫ", "structure": "ＲＣ", "district": "関前", "period": "2024年第2四半期", "walkMinutes": 13}, {"price": 1900, "area": 60.0, "unitPrice": 31.67, "buildingYear": 1969, "age": 56, "floorPlan": "３ＤＫ", "structure": "ＲＣ", "district": "関前", "period": "2024年第2四半期", "walkMinutes": 13}, {"price": 6200, "area": 85.0, "unitPrice": 72.94, "buildingYear": 2007, "age": 18, "floorPlan": "３ＬＤＫ", "structure": "ＲＣ", "district": "井口", "period": "2024年第2四半期", "walkMinutes": 17}, {"price": 4800, "area": 70.0, "unitPrice": 68.57, "buildingYear": 2007, "age": 18, "floorPlan": "３ＬＤＫ", "structure": "ＲＣ", "district": "井口", "period": "2024年第2四半期", "walkMinutes": 18}, {"price": 6500, "area": 65.0, "unitPrice": 100.0, "buildingYear": 2020, "age": 5, "floorPlan": "２ＬＤＫ", "structure": "ＲＣ", "district": "井口", "period": "2024年第2四半期", "walkMinutes": 13}, {"price": 6000, "area": 60.0, "unitPrice": 100.0, "buildingYear": 1999, "age": 26, "floorPlan": "３ＬＤＫ", "structure": "ＲＣ", "district": "上連雀", "period": "2024年第2四半期", "walkMinutes": 10}, {"price": 3800, "area": 65.0, "unitPrice": 58.46, "buildingYear": 2010, "age": 15, "floorPlan": "３ＬＤＫ", "structure": "ＲＣ", "district": "新町", "period": "2024年第2四半期", "walkMinutes": 19}, {"price": 6900, "area": 80.0, "unitPrice": 86.25, "buildingYear": 2004, "age": 21, "floorPlan": "３ＬＤＫ", "structure": "ＲＣ", "district": "境", "period": "2024年第1四半期", "walkMinutes": 11}, {"price": 4600, "area": 85.0, "unitPrice": 54.12, "buildingYear": 1977, "age": 48, "floorPlan": "１ＬＤＫ", "structure": "ＲＣ", "district": "境", "period": "2024年第1四半期", "walkMinutes": 10}, {"price": 6400, "area": 75.0, "unitPrice": 85.33, "buildingYear": 2009, "age": 16, "floorPlan": "２ＬＤＫ", "structure": "ＲＣ", "district": "境", "period": "2024年第1四半期", "walkMinutes": 9}, {"price": 5800, "area": 75.0, "unitPrice": 77.33, "buildingYear": 2013, "age": 12, "floorPlan": "３ＬＤＫ", "structure": "ＲＣ", "district": "桜堤", "period": "2024年第1四半期", "walkMinutes": null}, {"price": 6200, "area": 80.0, "unitPrice": 77.5, "buildingYear": 2012, "age": 13, "floorPlan": "３ＬＤＫ", "structure": "ＲＣ", "district": "桜堤", "period": "2024年第1四半期", "walkMinutes": null}, {"price": 6300, "area": 80.0, "unitPrice": 78.75, "buildingYear": 2012, "age": 13, "floorPlan": "３ＬＤＫ", "structure": "ＲＣ", "district": "桜堤", "period": "2024年第1四半期", "walkMinutes": null}, {"price": 6000, "area": 75.0, "unitPrice": 80.0, "buildingYear": 2013, "age": 12, "floorPlan": "３ＬＤＫ", "structure": "ＲＣ", "district": "桜堤", "period": "2024年第1四半期", "walkMinutes": null}, {"price": 7200, "area": 85.0, "unitPrice": 84.71, "buildingYear": 2012, "age": 13, "floorPlan": "３ＬＤＫ", "structure": "ＲＣ", "district": "桜堤", "period": "2024年第1四半期", "walkMinutes": null}, {"price": 2400, "area": 50.0, "unitPrice": 48.0, "buildingYear": 1969, "age": 56, "floorPlan": "２ＤＫ", "structure": "ＲＣ", "district": "関前", "period": "2024年第1四半期", "walkMinutes": 11}, {"price": 9600, "area": 75.0, "unitPrice": 128.0, "buildingYear": 2019, "age": 6, "floorPlan": "２ＬＤＫ", "structure": "ＲＣ", "district": "境南町", "period": "2024年第1四半期", "walkMinutes": 7}, {"price": 8700, "area": 70.0, "unitPrice": 124.29, "buildingYear": 2013, "age": 12, "floorPlan": "３ＬＤＫ", "structure": "ＲＣ", "district": "境南町", "period": "2024年第1四半期", "walkMinutes": 3}, {"price": 5700, "area": 75.0, "unitPrice": 76.0, "buildingYear": 2011, "age": 14, "floorPlan": "３ＬＤＫ", "structure": "ＲＣ", "district": "境南町", "period": "2024年第1四半期", "walkMinutes": 14}, {"price": 2900, "area": 55.0, "unitPrice": 52.73, "buildingYear": 1969, "age": 56, "floorPlan": "２ＬＤＫ", "structure": "ＳＲＣ", "district": "境南町", "period": "2024年第1四半期", "walkMinutes": 3}, {"price": 9600, "area": 70.0, "unitPrice": 137.14, "buildingYear": 2019, "age": 6, "floorPlan": "２ＬＤＫ", "structure": "ＲＣ", "district": "境南町", "period": "2024年第1四半期", "walkMinutes": 5}, {"price": 7000, "area": 75.0, "unitPrice": 93.33, "buildingYear": 2004, "age": 21, "floorPlan": "３ＬＤＫ", "structure": "ＲＣ", "district": "境", "period": "2024年第1四半期", "walkMinutes": 9}, {"price": 6400, "area": 65.0, "unitPrice": 98.46, "buildingYear": 2009, "age": 16, "floorPlan": "２ＬＤＫ", "structure": "ＲＣ", "district": "境", "period": "2024年第1四半期", "walkMinutes": 11}, {"price": 6000, "area": 70.0, "unitPrice": 85.71, "buildingYear": 2013, "age": 12, "floorPlan": "３ＬＤＫ", "structure": "ＲＣ", "district": "桜堤", "period": "2024年第1四半期", "walkMinutes": 21}, {"price": 7200, "area": 80.0, "unitPrice": 90.0, "buildingYear": 2012, "age": 13, "floorPlan": "３ＬＤＫ", "structure": "ＲＣ", "district": "桜堤", "period": "2024年第1四半期", "walkMinutes": 23}, {"price": 4000, "area": 35.0, "unitPrice": 114.29, "buildingYear": 2022, "age": 3, "floorPlan": "１ＬＤＫ", "structure": "ＲＣ", "district": "井口", "period": "2024年第1四半期", "walkMinutes": 10}, {"price": 4300, "area": 65.0, "unitPrice": 66.15, "buildingYear": 2007, "age": 18, "floorPlan": "２ＬＤＫ", "structure": "ＲＣ", "district": "井口", "period": "2024年第1四半期", "walkMinutes": 18}, {"price": 4800, "area": 40.0, "unitPrice": 120.0, "buildingYear": 2022, "age": 3, "floorPlan": "１ＬＤＫ", "structure": "ＲＣ", "district": "井口", "period": "2024年第1四半期", "walkMinutes": 9}, {"price": 4000, "area": 30.0, "unitPrice": 133.33, "buildingYear": 2022, "age": 3, "floorPlan": "１ＬＤＫ", "structure": "ＲＣ", "district": "井口", "period": "2024年第1四半期", "walkMinutes": 10}, {"price": 5800, "area": 60.0, "unitPrice": 96.67, "buildingYear": 1999, "age": 26, "floorPlan": "３ＬＤＫ", "structure": "ＲＣ", "district": "上連雀", "period": "2024年第1四半期", "walkMinutes": 10}, {"price": 7400, "area": 75.0, "unitPrice": 98.67, "buildingYear": 2013, "age": 12, "floorPlan": "３ＬＤＫ", "structure": "ＲＣ", "district": "境", "period": "2023年第4四半期", "walkMinutes": 2}, {"price": 7000, "area": 80.0, "unitPrice": 87.5, "buildingYear": 2004, "age": 21, "floorPlan": "３ＬＤＫ", "structure": "ＲＣ", "district": "境", "period": "2023年第4四半期", "walkMinutes": 10}, {"price": 3700, "area": 70.0, "unitPrice": 52.86, "buildingYear": 1980, "age": 45, "floorPlan": "２ＤＫ＋Ｓ", "structure": "ＲＣ", "district": "境", "period": "2023年第4四半期", "walkMinutes": 12}, {"price": 880, "area": 20.0, "unitPrice": 44.0, "buildingYear": 1987, "age": 38, "floorPlan": "２Ｋ", "structure": "ＲＣ", "district": "境", "period": "2023年第4四半期", "walkMinutes": 6}, {"price": 6000, "area": 80.0, "unitPrice": 75.0, "buildingYear": 2012, "age": 13, "floorPlan": "３ＬＤＫ", "structure": "ＲＣ", "district": "桜堤", "period": "2023年第4四半期", "walkMinutes": 23}, {"price": 6300, "area": 90.0, "unitPrice": 70.0, "buildingYear": 2012, "age": 13, "floorPlan": "３ＬＤＫ", "structure": "ＲＣ", "district": "桜堤", "period": "2023年第4四半期", "walkMinutes": null}, {"price": 6000, "area": 75.0, "unitPrice": 80.0, "buildingYear": 2013, "age": 12, "floorPlan": "３ＬＤＫ", "structure": "ＲＣ", "district": "桜堤", "period": "2023年第4四半期", "walkMinutes": null}, {"price": 1800, "area": 45.0, "unitPrice": 40.0, "buildingYear": 1969, "age": 56, "floorPlan": "２ＤＫ", "structure": "ＲＣ", "district": "関前", "period": "2023年第4四半期", "walkMinutes": 11}, {"price": 7000, "area": 55.0, "unitPrice": 127.27, "buildingYear": 2013, "age": 12, "floorPlan": "２ＬＤＫ", "structure": "ＲＣ", "district": "境南町", "period": "2023年第4四半期", "walkMinutes": 3}, {"price": 4000, "area": 55.0, "unitPrice": 72.73, "buildingYear": 1995, "age": 30, "floorPlan": "２ＬＤＫ", "structure": "ＲＣ", "district": "境南町", "period": "2023年第4四半期", "walkMinutes": 7}, {"price": 840, "area": 20.0, "unitPrice": 42.0, "buildingYear": 1985, "age": 40, "floorPlan": "１Ｒ", "structure": "ＳＲＣ", "district": "境南町", "period": "2023年第4四半期", "walkMinutes": 3}, {"price": 4600, "area": 65.0, "unitPrice": 70.77, "buildingYear": 1977, "age": 48, "floorPlan": "２ＬＤＫ", "structure": "ＳＲＣ", "district": "境南町", "period": "2023年第4四半期", "walkMinutes": 7}, {"price": 1600, "area": 30.0, "unitPrice": 53.33, "buildingYear": 1984, "age": 41, "floorPlan": "２Ｋ", "structure": "ＲＣ", "district": "境南町", "period": "2023年第4四半期", "walkMinutes": 4}, {"price": 7300, "area": 80.0, "unitPrice": 91.25, "buildingYear": 2005, "age": 20, "floorPlan": "３ＬＤＫ", "structure": "ＲＣ", "district": "境南町", "period": "2023年第4四半期", "walkMinutes": 7}, {"price": 9300, "area": 75.0, "unitPrice": 124.0, "buildingYear": 2018, "age": 7, "floorPlan": "３ＬＤＫ", "structure": "ＲＣ", "district": "境南町", "period": "2023年第4四半期", "walkMinutes": 6}, {"price": 4600, "area": 45.0, "unitPrice": 102.22, "buildingYear": 2015, "age": 10, "floorPlan": "１ＬＤＫ", "structure": "ＲＣ", "district": "境南町", "period": "2023年第4四半期", "walkMinutes": 4}, {"price": 970, "area": 15.0, "unitPrice": 64.67, "buildingYear": 1985, "age": 40, "floorPlan": "１Ｋ", "structure": "ＳＲＣ", "district": "境南町", "period": "2023年第4四半期", "walkMinutes": 3}, {"price": 5500, "area": 80.0, "unitPrice": 68.75, "buildingYear": 1989, "age": 36, "floorPlan": "３ＬＤＫ", "structure": "ＲＣ", "district": "境南町", "period": "2023年第4四半期", "walkMinutes": 14}, {"price": 3800, "area": 55.0, "unitPrice": 69.09, "buildingYear": 1973, "age": 52, "floorPlan": "", "structure": "ＲＣ", "district": "境南町", "period": "2023年第4四半期", "walkMinutes": 7}, {"price": 7000, "area": 50.0, "unitPrice": 140.0, "buildingYear": 2013, "age": 12, "floorPlan": "２ＬＤＫ", "structure": "ＲＣ", "district": "境南町", "period": "2023年第4四半期", "walkMinutes": 2}, {"price": 1100, "area": 15.0, "unitPrice": 73.33, "buildingYear": 2005, "age": 20, "floorPlan": "１Ｋ", "structure": "ＲＣ", "district": "関前", "period": "2023年第4四半期", "walkMinutes": 17}, {"price": 5700, "area": 65.0, "unitPrice": 87.69, "buildingYear": 2020, "age": 5, "floorPlan": "２ＬＤＫ＋Ｓ", "structure": "ＲＣ", "district": "井口", "period": "2023年第4四半期", "walkMinutes": 13}, {"price": 4200, "area": 70.0, "unitPrice": 60.0, "buildingYear": 2000, "age": 25, "floorPlan": "３ＬＤＫ", "structure": "ＲＣ", "district": "井口", "period": "2023年第4四半期", "walkMinutes": 17}, {"price": 3000, "area": 70.0, "unitPrice": 42.86, "buildingYear": 1974, "age": 51, "floorPlan": "２ＬＤＫ", "structure": "ＲＣ", "district": "井口", "period": "2023年第4四半期", "walkMinutes": 11}, {"price": 4500, "area": 75.0, "unitPrice": 60.0, "buildingYear": 2005, "age": 20, "floorPlan": "３ＬＤＫ", "structure": "ＲＣ", "district": "深大寺", "period": "2023年第4四半期", "walkMinutes": 19}, {"price": 9800, "area": 135.0, "unitPrice": 72.59, "buildingYear": 2010, "age": 15, "floorPlan": "３ＬＤＫ", "structure": "ＲＣ", "district": "向台町", "period": "2023年第4四半期", "walkMinutes": null}]